cli_tool_audit/__about__.py
cli_tool_audit/__init__.py
cli_tool_audit/__main__.py
cli_tool_audit/audit_cache.py
cli_tool_audit/audit_manager.py
cli_tool_audit/call_and_compatible.py
cli_tool_audit/call_tools.py
cli_tool_audit/compatibility.py
cli_tool_audit/compatibility_complex.py
cli_tool_audit/config_manager.py
cli_tool_audit/config_reader.py
cli_tool_audit/freeze.py
cli_tool_audit/interactive.py
cli_tool_audit/json_utils.py
cli_tool_audit/known_switches.py
cli_tool_audit/logging_config.py
cli_tool_audit/models.py
cli_tool_audit/policy.py
cli_tool_audit/py.typed
cli_tool_audit/version_parsing.py
cli_tool_audit/view_npm_stress_test.py
cli_tool_audit/view_pipx_stress_test.py
cli_tool_audit/view_venv_stress_test.py
cli_tool_audit/views.py
cli_tool_audit-3.1.0.dist-info/LICENSE
cli_tool_audit-3.1.0.dist-info/METADATA
cli_tool_audit-3.1.0.dist-info/WHEEL
cli_tool_audit-3.1.0.dist-info/entry_points.txt
cli_tool_audit-3.1.0.dist-info/RECORD
