Metadata-Version: 2.1
Name: cli_tool_audit
Version: 3.1.0
Summary: Audit for existence and version number of cli tools.
Home-page: https://github.com/matthewdeanmartin/cli_tool_audit
License: MIT
Keywords: cli tooling,version numbers
Author: Matthew Martin
Author-email: matthewdeanmartin@gmail.com
Requires-Python: >=3.9,<4.0
Classifier: Development Status :: 4 - Beta
Classifier: Intended Audience :: Developers
Classifier: License :: OSI Approved :: MIT License
Classifier: Operating System :: OS Independent
Classifier: Programming Language :: Python
Classifier: Programming Language :: Python :: 3
Classifier: Programming Language :: Python :: 3.9
Classifier: Programming Language :: Python :: 3.10
Classifier: Programming Language :: Python :: 3.11
Classifier: Programming Language :: Python :: 3.12
Requires-Dist: colorama (>=0.4.6)
Requires-Dist: colorlog (>=6.8.0)
Requires-Dist: packaging (>=23.2)
Requires-Dist: prettytable (>=3.9.0)
Requires-Dist: semver (>=3.0.2)
Requires-Dist: toml (>=0.10.2)
Requires-Dist: tomlkit (>=0.12.3)
Requires-Dist: tqdm (>=4.66.1)
Requires-Dist: whichcraft (>=0.6.1)
Project-URL: Bug Tracker, https://github.com/matthewdeanmartin/cli_tool_audit/issues
Project-URL: Change Log, https://github.com/matthewdeanmartin/cli_tool_audit/blob/main/CHANGELOG.md
Project-URL: Documentation, https://matthewdeanmartin.github.io/cli_tool_audit/cli_tool_audit/index.html
Project-URL: Repository, https://github.com/matthewdeanmartin/cli_tool_audit
